modelitool/__init__.py
modelitool/combitabconvert.py
modelitool/corrai_connector.py
modelitool/simulate.py
modelitool/weather.py
modelitool-0.1.1.dist-info/LICENCE.md
modelitool-0.1.1.dist-info/METADATA
modelitool-0.1.1.dist-info/WHEEL
modelitool-0.1.1.dist-info/top_level.txt
modelitool-0.1.1.dist-info/RECORD
