Metadata-Version: 2.1
Name: modelitool
Version: 0.1.1
Summary: Tools for Modelica
Home-page: https://github.com/BuildingEnergySimulationTools/modelitool
Author: Nobatek/INEF4
Author-email: bdurandestebe@nobatek.com
License: License :: OSI Approved :: BSD License
Classifier: Development Status :: 4 - Beta
Classifier: Intended Audience :: Developers
Classifier: Topic :: Scientific/Engineering
Classifier: Programming Language :: Python :: 3.10
Classifier: Programming Language :: Python :: 3.11
Requires-Python: >=3.10
License-File: LICENCE.md
Requires-Dist: pandas >=1.5.0
Requires-Dist: numpy >=1.17.3
Requires-Dist: OMPython >=3.5.2
Requires-Dist: corrai >=0.3.0
